{ "compressionlevel":-1,
 "editorsettings":
    {
     "export":
        {
         "format":"json1",
         "target":"bloxorz29.json"
        }
    },
 "height":16,
 "infinite":true,
 "layers":[
        {
         "chunks":[],
         "height":0,
         "id":1,
         "name":"Tile Layer 1",
         "opacity":1,
         "startx":0,
         "starty":0,
         "type":"tilelayer",
         "visible":true,
         "width":0,
         "x":0,
         "y":0
        }, 
        {
         "color":"#aaaa7f",
         "draworder":"topdown",
         "id":5,
         "name":"normal",
         "objects":[
                {
                 "height":50,
                 "id":3609,
                 "name":"",
                 "rotation":0,
                 "type":"",
                 "visible":true,
                 "width":50,
                 "x":0,
                 "y":0
                }, 
                {
                 "height":50,
                 "id":3610,
                 "name":"",
                 "rotation":0,
                 "type":"",
                 "visible":true,
                 "width":50,
                 "x":0,
                 "y":50
                }, 
                {
                 "height":50,
                 "id":3611,
                 "name":"",
                 "rotation":0,
                 "type":"",
                 "visible":true,
                 "width":50,
                 "x":50,
                 "y":150
                }, 
                {
                 "height":50,
                 "id":3612,
                 "name":"",
                 "rotation":0,
                 "type":"",
                 "visible":true,
                 "width":50,
                 "x":150,
                 "y":150
                }, 
                {
                 "height":50,
                 "id":3613,
                 "name":"",
                 "rotation":0,
                 "type":"",
                 "visible":true,
                 "width":50,
                 "x":0,
                 "y":250
                }, 
                {
                 "height":50,
                 "id":3614,
                 "name":"",
                 "rotation":0,
                 "type":"",
                 "visible":true,
                 "width":50,
                 "x":-100,
                 "y":200
                }, 
                {
                 "height":50,
                 "id":3615,
                 "name":"",
                 "rotation":0,
                 "type":"",
                 "visible":true,
                 "width":50,
                 "x":250,
                 "y":100
                }, 
                {
                 "height":50,
                 "id":3616,
                 "name":"",
                 "rotation":0,
                 "type":"",
                 "visible":true,
                 "width":50,
                 "x":300,
                 "y":100
                }, 
                {
                 "height":50,
                 "id":3617,
                 "name":"",
                 "rotation":0,
                 "type":"",
                 "visible":true,
                 "width":50,
                 "x":300,
                 "y":150
                }, 
                {
                 "height":50,
                 "id":3618,
                 "name":"",
                 "rotation":0,
                 "type":"",
                 "visible":true,
                 "width":50,
                 "x":300,
                 "y":-50
                }, 
                {
                 "height":50,
                 "id":3619,
                 "name":"",
                 "rotation":0,
                 "type":"",
                 "visible":true,
                 "width":50,
                 "x":350,
                 "y":-50
                }, 
                {
                 "height":50,
                 "id":3656,
                 "name":"",
                 "rotation":0,
                 "type":"",
                 "visible":true,
                 "width":50,
                 "x":500,
                 "y":250
                }, 
                {
                 "height":50,
                 "id":3657,
                 "name":"",
                 "rotation":0,
                 "type":"",
                 "visible":true,
                 "width":50,
                 "x":500,
                 "y":200
                }, 
                {
                 "height":50,
                 "id":3658,
                 "name":"",
                 "rotation":0,
                 "type":"",
                 "visible":true,
                 "width":50,
                 "x":550,
                 "y":150
                }, 
                {
                 "height":50,
                 "id":3659,
                 "name":"",
                 "rotation":0,
                 "type":"",
                 "visible":true,
                 "width":50,
                 "x":550,
                 "y":100
                }, 
                {
                 "height":50,
                 "id":3660,
                 "name":"",
                 "rotation":0,
                 "type":"",
                 "visible":true,
                 "width":50,
                 "x":600,
                 "y":100
                }, 
                {
                 "height":50,
                 "id":3661,
                 "name":"",
                 "rotation":0,
                 "type":"",
                 "visible":true,
                 "width":50,
                 "x":600,
                 "y":50
                }, 
                {
                 "height":50,
                 "id":3662,
                 "name":"",
                 "rotation":0,
                 "type":"",
                 "visible":true,
                 "width":50,
                 "x":600,
                 "y":0
                }, 
                {
                 "height":50,
                 "id":3663,
                 "name":"",
                 "rotation":0,
                 "type":"",
                 "visible":true,
                 "width":50,
                 "x":600,
                 "y":-50
                }, 
                {
                 "height":50,
                 "id":3664,
                 "name":"",
                 "rotation":0,
                 "type":"",
                 "visible":true,
                 "width":50,
                 "x":550,
                 "y":-50
                }, 
                {
                 "height":50,
                 "id":3665,
                 "name":"",
                 "rotation":0,
                 "type":"",
                 "visible":true,
                 "width":50,
                 "x":500,
                 "y":-50
                }, 
                {
                 "height":50,
                 "id":3666,
                 "name":"",
                 "rotation":0,
                 "type":"",
                 "visible":true,
                 "width":50,
                 "x":550,
                 "y":-100
                }, 
                {
                 "height":50,
                 "id":3667,
                 "name":"",
                 "rotation":0,
                 "type":"",
                 "visible":true,
                 "width":50,
                 "x":550,
                 "y":-150
                }, 
                {
                 "height":50,
                 "id":3668,
                 "name":"",
                 "rotation":0,
                 "type":"",
                 "visible":true,
                 "width":50,
                 "x":550,
                 "y":-200
                }, 
                {
                 "height":50,
                 "id":3671,
                 "name":"",
                 "rotation":0,
                 "type":"",
                 "visible":true,
                 "width":50,
                 "x":500,
                 "y":-200
                }, 
                {
                 "height":50,
                 "id":3672,
                 "name":"",
                 "rotation":0,
                 "type":"",
                 "visible":true,
                 "width":50,
                 "x":450,
                 "y":-200
                }, 
                {
                 "height":50,
                 "id":3673,
                 "name":"",
                 "rotation":0,
                 "type":"",
                 "visible":true,
                 "width":50,
                 "x":400,
                 "y":-200
                }, 
                {
                 "height":50,
                 "id":3676,
                 "name":"",
                 "rotation":0,
                 "type":"",
                 "visible":true,
                 "width":50,
                 "x":250,
                 "y":-200
                }, 
                {
                 "height":50,
                 "id":3677,
                 "name":"",
                 "rotation":0,
                 "type":"",
                 "visible":true,
                 "width":50,
                 "x":200,
                 "y":-200
                }, 
                {
                 "height":50,
                 "id":3678,
                 "name":"",
                 "rotation":0,
                 "type":"",
                 "visible":true,
                 "width":50,
                 "x":200,
                 "y":-150
                }, 
                {
                 "height":50,
                 "id":3679,
                 "name":"",
                 "rotation":0,
                 "type":"",
                 "visible":true,
                 "width":50,
                 "x":150,
                 "y":-200
                }, 
                {
                 "height":50,
                 "id":3680,
                 "name":"",
                 "rotation":0,
                 "type":"",
                 "visible":true,
                 "width":50,
                 "x":150,
                 "y":-150
                }, 
                {
                 "height":50,
                 "id":3681,
                 "name":"",
                 "rotation":0,
                 "type":"",
                 "visible":true,
                 "width":50,
                 "x":150,
                 "y":-100
                }, 
                {
                 "height":50,
                 "id":3682,
                 "name":"",
                 "rotation":0,
                 "type":"",
                 "visible":true,
                 "width":50,
                 "x":100,
                 "y":-100
                }, 
                {
                 "height":50,
                 "id":3683,
                 "name":"",
                 "rotation":0,
                 "type":"",
                 "visible":true,
                 "width":50,
                 "x":50,
                 "y":-100
                }, 
                {
                 "height":50,
                 "id":3684,
                 "name":"",
                 "rotation":0,
                 "type":"",
                 "visible":true,
                 "width":50,
                 "x":50,
                 "y":-150
                }, 
                {
                 "height":50,
                 "id":3685,
                 "name":"",
                 "rotation":0,
                 "type":"",
                 "visible":true,
                 "width":50,
                 "x":50,
                 "y":-200
                }, 
                {
                 "height":50,
                 "id":3686,
                 "name":"",
                 "rotation":0,
                 "type":"",
                 "visible":true,
                 "width":50,
                 "x":100,
                 "y":-200
                }],
         "opacity":1,
         "type":"objectgroup",
         "visible":true,
         "x":0,
         "y":0
        }, 
        {
         "color":"#34ebab",
         "draworder":"topdown",
         "id":2,
         "name":"bridge",
         "objects":[
                {
                 "height":50,
                 "id":3464,
                 "name":"",
                 "properties":
                    {
                     "id":"bridgeA",
                     "startActivated":true
                    },
                 "propertytypes":
                    {
                     "id":"string",
                     "startActivated":"bool"
                    },
                 "rotation":0,
                 "type":"",
                 "visible":true,
                 "width":50,
                 "x":400,
                 "y":-50
                }, 
                {
                 "height":50,
                 "id":3687,
                 "name":"",
                 "properties":
                    {
                     "id":"bridgeA",
                     "startActivated":true
                    },
                 "propertytypes":
                    {
                     "id":"string",
                     "startActivated":"bool"
                    },
                 "rotation":0,
                 "type":"",
                 "visible":true,
                 "width":50,
                 "x":450,
                 "y":-50
                }, 
                {
                 "height":50,
                 "id":3688,
                 "name":"",
                 "properties":
                    {
                     "id":"bridgeB",
                     "startActivated":true
                    },
                 "propertytypes":
                    {
                     "id":"string",
                     "startActivated":"bool"
                    },
                 "rotation":0,
                 "type":"",
                 "visible":true,
                 "width":50,
                 "x":550,
                 "y":200
                }, 
                {
                 "height":50,
                 "id":3691,
                 "name":"",
                 "properties":
                    {
                     "id":"bridgeC",
                     "startActivated":true
                    },
                 "propertytypes":
                    {
                     "id":"string",
                     "startActivated":"bool"
                    },
                 "rotation":0,
                 "type":"",
                 "visible":true,
                 "width":50,
                 "x":500,
                 "y":100
                }, 
                {
                 "height":50,
                 "id":3692,
                 "name":"",
                 "properties":
                    {
                     "id":"bridgeC",
                     "startActivated":true
                    },
                 "propertytypes":
                    {
                     "id":"string",
                     "startActivated":"bool"
                    },
                 "rotation":0,
                 "type":"",
                 "visible":true,
                 "width":50,
                 "x":350,
                 "y":100
                }],
         "opacity":1,
         "type":"objectgroup",
         "visible":true,
         "x":0,
         "y":0
        }, 
        {
         "color":"#ff0000",
         "draworder":"topdown",
         "id":3,
         "name":"goal",
         "objects":[
                {
                 "height":50,
                 "id":2610,
                 "name":"",
                 "rotation":0,
                 "type":"",
                 "visible":true,
                 "width":50,
                 "x":100,
                 "y":-150
                }],
         "opacity":1,
         "type":"objectgroup",
         "visible":true,
         "x":0,
         "y":0
        }, 
        {
         "color":"#55aaff",
         "draworder":"topdown",
         "id":4,
         "name":"button",
         "objects":[
                {
                 "height":50,
                 "id":3486,
                 "name":"",
                 "properties":
                    {
                     "activating":"bridgeA",
                     "hard":true,
                     "type":"on"
                    },
                 "propertytypes":
                    {
                     "activating":"string",
                     "hard":"bool",
                     "type":"string"
                    },
                 "rotation":0,
                 "type":"",
                 "visible":true,
                 "width":50,
                 "x":-50,
                 "y":50
                }, 
                {
                 "height":50,
                 "id":3689,
                 "name":"",
                 "properties":
                    {
                     "activating":"bridgeB",
                     "hard":true,
                     "type":"toggle"
                    },
                 "propertytypes":
                    {
                     "activating":"string",
                     "hard":"bool",
                     "type":"string"
                    },
                 "rotation":0,
                 "type":"",
                 "visible":true,
                 "width":50,
                 "x":500,
                 "y":150
                }, 
                {
                 "height":50,
                 "id":3690,
                 "name":"",
                 "properties":
                    {
                     "activating":"bridgeC",
                     "hard":true,
                     "type":"on"
                    },
                 "propertytypes":
                    {
                     "activating":"string",
                     "hard":"bool",
                     "type":"string"
                    },
                 "rotation":0,
                 "type":"",
                 "visible":true,
                 "width":50,
                 "x":600,
                 "y":-100
                }, 
                {
                 "height":50,
                 "id":3693,
                 "name":"",
                 "properties":
                    {
                     "activating":"bridgeA",
                     "hard":true,
                     "type":"off"
                    },
                 "propertytypes":
                    {
                     "activating":"string",
                     "hard":"bool",
                     "type":"string"
                    },
                 "rotation":0,
                 "type":"",
                 "visible":true,
                 "width":50,
                 "x":600,
                 "y":-100
                }],
         "opacity":1,
         "type":"objectgroup",
         "visible":true,
         "x":0,
         "y":0
        }, 
        {
         "color":"#000000",
         "draworder":"topdown",
         "id":6,
         "name":"border",
         "objects":[
                {
                 "height":50,
                 "id":3694,
                 "name":"",
                 "rotation":0,
                 "type":"",
                 "visible":true,
                 "width":50,
                 "x":50,
                 "y":-250
                }, 
                {
                 "height":50,
                 "id":3695,
                 "name":"",
                 "rotation":0,
                 "type":"",
                 "visible":true,
                 "width":50,
                 "x":100,
                 "y":-250
                }, 
                {
                 "height":50,
                 "id":3696,
                 "name":"",
                 "rotation":0,
                 "type":"",
                 "visible":true,
                 "width":50,
                 "x":150,
                 "y":-250
                }, 
                {
                 "height":50,
                 "id":3697,
                 "name":"",
                 "rotation":0,
                 "type":"",
                 "visible":true,
                 "width":50,
                 "x":200,
                 "y":-250
                }, 
                {
                 "height":50,
                 "id":3698,
                 "name":"",
                 "rotation":0,
                 "type":"",
                 "visible":true,
                 "width":50,
                 "x":250,
                 "y":-250
                }, 
                {
                 "height":50,
                 "id":3699,
                 "name":"",
                 "rotation":0,
                 "type":"",
                 "visible":true,
                 "width":50,
                 "x":300,
                 "y":-250
                }, 
                {
                 "height":50,
                 "id":3700,
                 "name":"",
                 "rotation":0,
                 "type":"",
                 "visible":true,
                 "width":50,
                 "x":350,
                 "y":-250
                }, 
                {
                 "height":50,
                 "id":3701,
                 "name":"",
                 "rotation":0,
                 "type":"",
                 "visible":true,
                 "width":50,
                 "x":400,
                 "y":-250
                }, 
                {
                 "height":50,
                 "id":3702,
                 "name":"",
                 "rotation":0,
                 "type":"",
                 "visible":true,
                 "width":50,
                 "x":450,
                 "y":-250
                }, 
                {
                 "height":50,
                 "id":3703,
                 "name":"",
                 "rotation":0,
                 "type":"",
                 "visible":true,
                 "width":50,
                 "x":500,
                 "y":-250
                }, 
                {
                 "height":50,
                 "id":3704,
                 "name":"",
                 "rotation":0,
                 "type":"",
                 "visible":true,
                 "width":50,
                 "x":550,
                 "y":-250
                }, 
                {
                 "height":50,
                 "id":3705,
                 "name":"",
                 "rotation":0,
                 "type":"",
                 "visible":true,
                 "width":50,
                 "x":600,
                 "y":-250
                }, 
                {
                 "height":50,
                 "id":3706,
                 "name":"",
                 "rotation":0,
                 "type":"",
                 "visible":true,
                 "width":50,
                 "x":600,
                 "y":-200
                }, 
                {
                 "height":50,
                 "id":3707,
                 "name":"",
                 "rotation":0,
                 "type":"",
                 "visible":true,
                 "width":50,
                 "x":600,
                 "y":-150
                }, 
                {
                 "height":50,
                 "id":3708,
                 "name":"",
                 "rotation":0,
                 "type":"",
                 "visible":true,
                 "width":50,
                 "x":650,
                 "y":-150
                }, 
                {
                 "height":50,
                 "id":3709,
                 "name":"",
                 "rotation":0,
                 "type":"",
                 "visible":true,
                 "width":50,
                 "x":650,
                 "y":-100
                }, 
                {
                 "height":50,
                 "id":3710,
                 "name":"",
                 "rotation":0,
                 "type":"",
                 "visible":true,
                 "width":50,
                 "x":650,
                 "y":-50
                }, 
                {
                 "height":50,
                 "id":3711,
                 "name":"",
                 "rotation":0,
                 "type":"",
                 "visible":true,
                 "width":50,
                 "x":650,
                 "y":0
                }, 
                {
                 "height":50,
                 "id":3712,
                 "name":"",
                 "rotation":0,
                 "type":"",
                 "visible":true,
                 "width":50,
                 "x":650,
                 "y":50
                }, 
                {
                 "height":50,
                 "id":3713,
                 "name":"",
                 "rotation":0,
                 "type":"",
                 "visible":true,
                 "width":50,
                 "x":650,
                 "y":100
                }, 
                {
                 "height":50,
                 "id":3714,
                 "name":"",
                 "rotation":0,
                 "type":"",
                 "visible":true,
                 "width":50,
                 "x":650,
                 "y":150
                }, 
                {
                 "height":50,
                 "id":3715,
                 "name":"",
                 "rotation":0,
                 "type":"",
                 "visible":true,
                 "width":50,
                 "x":600,
                 "y":150
                }, 
                {
                 "height":50,
                 "id":3716,
                 "name":"",
                 "rotation":0,
                 "type":"",
                 "visible":true,
                 "width":50,
                 "x":600,
                 "y":200
                }, 
                {
                 "height":50,
                 "id":3717,
                 "name":"",
                 "rotation":0,
                 "type":"",
                 "visible":true,
                 "width":50,
                 "x":600,
                 "y":250
                }, 
                {
                 "height":50,
                 "id":3718,
                 "name":"",
                 "rotation":0,
                 "type":"",
                 "visible":true,
                 "width":50,
                 "x":550,
                 "y":250
                }, 
                {
                 "height":50,
                 "id":3719,
                 "name":"",
                 "rotation":0,
                 "type":"",
                 "visible":true,
                 "width":50,
                 "x":550,
                 "y":300
                }, 
                {
                 "height":50,
                 "id":3720,
                 "name":"",
                 "rotation":0,
                 "type":"",
                 "visible":true,
                 "width":50,
                 "x":500,
                 "y":300
                }, 
                {
                 "height":50,
                 "id":3721,
                 "name":"",
                 "rotation":0,
                 "type":"",
                 "visible":true,
                 "width":50,
                 "x":450,
                 "y":300
                }, 
                {
                 "height":50,
                 "id":3722,
                 "name":"",
                 "rotation":0,
                 "type":"",
                 "visible":true,
                 "width":50,
                 "x":400,
                 "y":300
                }, 
                {
                 "height":50,
                 "id":3723,
                 "name":"",
                 "rotation":0,
                 "type":"",
                 "visible":true,
                 "width":50,
                 "x":350,
                 "y":300
                }, 
                {
                 "height":50,
                 "id":3724,
                 "name":"",
                 "rotation":0,
                 "type":"",
                 "visible":true,
                 "width":50,
                 "x":300,
                 "y":300
                }, 
                {
                 "height":50,
                 "id":3725,
                 "name":"",
                 "rotation":0,
                 "type":"",
                 "visible":true,
                 "width":50,
                 "x":250,
                 "y":300
                }, 
                {
                 "height":50,
                 "id":3726,
                 "name":"",
                 "rotation":0,
                 "type":"",
                 "visible":true,
                 "width":50,
                 "x":250,
                 "y":250
                }, 
                {
                 "height":50,
                 "id":3727,
                 "name":"",
                 "rotation":0,
                 "type":"",
                 "visible":true,
                 "width":50,
                 "x":200,
                 "y":250
                }, 
                {
                 "height":50,
                 "id":3728,
                 "name":"",
                 "rotation":0,
                 "type":"",
                 "visible":true,
                 "width":50,
                 "x":200,
                 "y":300
                }, 
                {
                 "height":50,
                 "id":3729,
                 "name":"",
                 "rotation":0,
                 "type":"",
                 "visible":true,
                 "width":50,
                 "x":150,
                 "y":300
                }, 
                {
                 "height":50,
                 "id":3730,
                 "name":"",
                 "rotation":0,
                 "type":"",
                 "visible":true,
                 "width":50,
                 "x":100,
                 "y":300
                }, 
                {
                 "height":50,
                 "id":3731,
                 "name":"",
                 "rotation":0,
                 "type":"",
                 "visible":true,
                 "width":50,
                 "x":50,
                 "y":300
                }, 
                {
                 "height":50,
                 "id":3732,
                 "name":"",
                 "rotation":0,
                 "type":"",
                 "visible":true,
                 "width":50,
                 "x":0,
                 "y":300
                }, 
                {
                 "height":50,
                 "id":3733,
                 "name":"",
                 "rotation":0,
                 "type":"",
                 "visible":true,
                 "width":50,
                 "x":-50,
                 "y":300
                }, 
                {
                 "height":50,
                 "id":3734,
                 "name":"",
                 "rotation":0,
                 "type":"",
                 "visible":true,
                 "width":50,
                 "x":-100,
                 "y":300
                }, 
                {
                 "height":50,
                 "id":3735,
                 "name":"",
                 "rotation":0,
                 "type":"",
                 "visible":true,
                 "width":50,
                 "x":-100,
                 "y":250
                }, 
                {
                 "height":50,
                 "id":3736,
                 "name":"",
                 "rotation":0,
                 "type":"",
                 "visible":true,
                 "width":50,
                 "x":-150,
                 "y":250
                }, 
                {
                 "height":50,
                 "id":3737,
                 "name":"",
                 "rotation":0,
                 "type":"",
                 "visible":true,
                 "width":50,
                 "x":-150,
                 "y":200
                }, 
                {
                 "height":50,
                 "id":3738,
                 "name":"",
                 "rotation":0,
                 "type":"",
                 "visible":true,
                 "width":50,
                 "x":-150,
                 "y":150
                }, 
                {
                 "height":50,
                 "id":3739,
                 "name":"",
                 "rotation":0,
                 "type":"",
                 "visible":true,
                 "width":50,
                 "x":-150,
                 "y":100
                }, 
                {
                 "height":50,
                 "id":3740,
                 "name":"",
                 "rotation":0,
                 "type":"",
                 "visible":true,
                 "width":50,
                 "x":-150,
                 "y":50
                }, 
                {
                 "height":50,
                 "id":3741,
                 "name":"",
                 "rotation":0,
                 "type":"",
                 "visible":true,
                 "width":50,
                 "x":-100,
                 "y":50
                }, 
                {
                 "height":50,
                 "id":3742,
                 "name":"",
                 "rotation":0,
                 "type":"",
                 "visible":true,
                 "width":50,
                 "x":-100,
                 "y":0
                }, 
                {
                 "height":50,
                 "id":3743,
                 "name":"",
                 "rotation":0,
                 "type":"",
                 "visible":true,
                 "width":50,
                 "x":-50,
                 "y":0
                }, 
                {
                 "height":50,
                 "id":3744,
                 "name":"",
                 "rotation":0,
                 "type":"",
                 "visible":true,
                 "width":50,
                 "x":-50,
                 "y":-50
                }, 
                {
                 "height":50,
                 "id":3745,
                 "name":"",
                 "rotation":0,
                 "type":"",
                 "visible":true,
                 "width":50,
                 "x":0,
                 "y":-50
                }, 
                {
                 "height":50,
                 "id":3746,
                 "name":"",
                 "rotation":0,
                 "type":"",
                 "visible":true,
                 "width":50,
                 "x":50,
                 "y":-50
                }, 
                {
                 "height":50,
                 "id":3747,
                 "name":"",
                 "rotation":0,
                 "type":"",
                 "visible":true,
                 "width":50,
                 "x":50,
                 "y":0
                }, 
                {
                 "height":50,
                 "id":3748,
                 "name":"",
                 "rotation":0,
                 "type":"",
                 "visible":true,
                 "width":50,
                 "x":100,
                 "y":0
                }, 
                {
                 "height":50,
                 "id":3749,
                 "name":"",
                 "rotation":0,
                 "type":"",
                 "visible":true,
                 "width":50,
                 "x":100,
                 "y":50
                }, 
                {
                 "height":50,
                 "id":3750,
                 "name":"",
                 "rotation":0,
                 "type":"",
                 "visible":true,
                 "width":50,
                 "x":100,
                 "y":100
                }, 
                {
                 "height":50,
                 "id":3751,
                 "name":"",
                 "rotation":0,
                 "type":"",
                 "visible":true,
                 "width":50,
                 "x":150,
                 "y":100
                }, 
                {
                 "height":50,
                 "id":3752,
                 "name":"",
                 "rotation":0,
                 "type":"",
                 "visible":true,
                 "width":50,
                 "x":200,
                 "y":100
                }, 
                {
                 "height":50,
                 "id":3753,
                 "name":"",
                 "rotation":0,
                 "type":"",
                 "visible":true,
                 "width":50,
                 "x":200,
                 "y":50
                }, 
                {
                 "height":50,
                 "id":3754,
                 "name":"",
                 "rotation":0,
                 "type":"",
                 "visible":true,
                 "width":50,
                 "x":200,
                 "y":0
                }, 
                {
                 "height":50,
                 "id":3755,
                 "name":"",
                 "rotation":0,
                 "type":"",
                 "visible":true,
                 "width":50,
                 "x":200,
                 "y":-50
                }, 
                {
                 "height":50,
                 "id":3756,
                 "name":"",
                 "rotation":0,
                 "type":"",
                 "visible":true,
                 "width":50,
                 "x":200,
                 "y":-100
                }, 
                {
                 "height":50,
                 "id":3757,
                 "name":"",
                 "rotation":0,
                 "type":"",
                 "visible":true,
                 "width":50,
                 "x":250,
                 "y":-100
                }, 
                {
                 "height":50,
                 "id":3758,
                 "name":"",
                 "rotation":0,
                 "type":"",
                 "visible":true,
                 "width":50,
                 "x":300,
                 "y":-100
                }, 
                {
                 "height":50,
                 "id":3759,
                 "name":"",
                 "rotation":0,
                 "type":"",
                 "visible":true,
                 "width":50,
                 "x":350,
                 "y":-100
                }, 
                {
                 "height":50,
                 "id":3760,
                 "name":"",
                 "rotation":0,
                 "type":"",
                 "visible":true,
                 "width":50,
                 "x":400,
                 "y":-100
                }, 
                {
                 "height":50,
                 "id":3761,
                 "name":"",
                 "rotation":0,
                 "type":"",
                 "visible":true,
                 "width":50,
                 "x":450,
                 "y":-100
                }, 
                {
                 "height":50,
                 "id":3762,
                 "name":"",
                 "rotation":0,
                 "type":"",
                 "visible":true,
                 "width":50,
                 "x":500,
                 "y":-100
                }, 
                {
                 "height":50,
                 "id":3763,
                 "name":"",
                 "rotation":0,
                 "type":"",
                 "visible":true,
                 "width":50,
                 "x":500,
                 "y":-150
                }, 
                {
                 "height":50,
                 "id":3764,
                 "name":"",
                 "rotation":0,
                 "type":"",
                 "visible":true,
                 "width":50,
                 "x":450,
                 "y":-150
                }, 
                {
                 "height":50,
                 "id":3765,
                 "name":"",
                 "rotation":0,
                 "type":"",
                 "visible":true,
                 "width":50,
                 "x":400,
                 "y":-150
                }, 
                {
                 "height":50,
                 "id":3766,
                 "name":"",
                 "rotation":0,
                 "type":"",
                 "visible":true,
                 "width":50,
                 "x":350,
                 "y":-150
                }, 
                {
                 "height":50,
                 "id":3767,
                 "name":"",
                 "rotation":0,
                 "type":"",
                 "visible":true,
                 "width":50,
                 "x":300,
                 "y":-150
                }, 
                {
                 "height":50,
                 "id":3768,
                 "name":"",
                 "rotation":0,
                 "type":"",
                 "visible":true,
                 "width":50,
                 "x":250,
                 "y":-150
                }, 
                {
                 "height":50,
                 "id":3769,
                 "name":"",
                 "rotation":0,
                 "type":"",
                 "visible":true,
                 "width":50,
                 "x":350,
                 "y":0
                }, 
                {
                 "height":50,
                 "id":3770,
                 "name":"",
                 "rotation":0,
                 "type":"",
                 "visible":true,
                 "width":50,
                 "x":350,
                 "y":50
                }, 
                {
                 "height":50,
                 "id":3771,
                 "name":"",
                 "rotation":0,
                 "type":"",
                 "visible":true,
                 "width":50,
                 "x":400,
                 "y":50
                }, 
                {
                 "height":50,
                 "id":3772,
                 "name":"",
                 "rotation":0,
                 "type":"",
                 "visible":true,
                 "width":50,
                 "x":400,
                 "y":0
                }, 
                {
                 "height":50,
                 "id":3773,
                 "name":"",
                 "rotation":0,
                 "type":"",
                 "visible":true,
                 "width":50,
                 "x":450,
                 "y":0
                }, 
                {
                 "height":50,
                 "id":3774,
                 "name":"",
                 "rotation":0,
                 "type":"",
                 "visible":true,
                 "width":50,
                 "x":450,
                 "y":50
                }, 
                {
                 "height":50,
                 "id":3775,
                 "name":"",
                 "rotation":0,
                 "type":"",
                 "visible":true,
                 "width":50,
                 "x":500,
                 "y":50
                }, 
                {
                 "height":50,
                 "id":3776,
                 "name":"",
                 "rotation":0,
                 "type":"",
                 "visible":true,
                 "width":50,
                 "x":500,
                 "y":0
                }, 
                {
                 "height":50,
                 "id":3777,
                 "name":"",
                 "rotation":0,
                 "type":"",
                 "visible":true,
                 "width":50,
                 "x":550,
                 "y":0
                }, 
                {
                 "height":50,
                 "id":3778,
                 "name":"",
                 "rotation":0,
                 "type":"",
                 "visible":true,
                 "width":50,
                 "x":550,
                 "y":50
                }, 
                {
                 "height":50,
                 "id":3779,
                 "name":"",
                 "rotation":0,
                 "type":"",
                 "visible":true,
                 "width":50,
                 "x":400,
                 "y":100
                }, 
                {
                 "height":50,
                 "id":3780,
                 "name":"",
                 "rotation":0,
                 "type":"",
                 "visible":true,
                 "width":50,
                 "x":450,
                 "y":100
                }, 
                {
                 "height":50,
                 "id":3781,
                 "name":"",
                 "rotation":0,
                 "type":"",
                 "visible":true,
                 "width":50,
                 "x":450,
                 "y":150
                }, 
                {
                 "height":50,
                 "id":3782,
                 "name":"",
                 "rotation":0,
                 "type":"",
                 "visible":true,
                 "width":50,
                 "x":400,
                 "y":150
                }, 
                {
                 "height":50,
                 "id":3783,
                 "name":"",
                 "rotation":0,
                 "type":"",
                 "visible":true,
                 "width":50,
                 "x":100,
                 "y":-50
                }, 
                {
                 "height":50,
                 "id":3784,
                 "name":"",
                 "rotation":0,
                 "type":"",
                 "visible":true,
                 "width":50,
                 "x":150,
                 "y":-50
                }, 
                {
                 "height":50,
                 "id":3785,
                 "name":"",
                 "rotation":0,
                 "type":"",
                 "visible":true,
                 "width":50,
                 "x":0,
                 "y":-250
                }, 
                {
                 "height":50,
                 "id":3786,
                 "name":"",
                 "rotation":0,
                 "type":"",
                 "visible":true,
                 "width":50,
                 "x":0,
                 "y":-200
                }, 
                {
                 "height":50,
                 "id":3787,
                 "name":"",
                 "rotation":0,
                 "type":"",
                 "visible":true,
                 "width":50,
                 "x":0,
                 "y":-150
                }, 
                {
                 "height":50,
                 "id":3788,
                 "name":"",
                 "rotation":0,
                 "type":"",
                 "visible":true,
                 "width":50,
                 "x":0,
                 "y":-100
                }],
         "opacity":1,
         "type":"objectgroup",
         "visible":true,
         "x":0,
         "y":0
        }, 
        {
         "color":"#f49f0a",
         "draworder":"topdown",
         "id":9,
         "name":"weak",
         "objects":[
                {
                 "height":50,
                 "id":3620,
                 "name":"",
                 "rotation":0,
                 "type":"",
                 "visible":true,
                 "width":50,
                 "x":50,
                 "y":50
                }, 
                {
                 "height":50,
                 "id":3621,
                 "name":"",
                 "rotation":0,
                 "type":"",
                 "visible":true,
                 "width":50,
                 "x":50,
                 "y":100
                }, 
                {
                 "height":50,
                 "id":3622,
                 "name":"",
                 "rotation":0,
                 "type":"",
                 "visible":true,
                 "width":50,
                 "x":0,
                 "y":100
                }, 
                {
                 "height":50,
                 "id":3623,
                 "name":"",
                 "rotation":0,
                 "type":"",
                 "visible":true,
                 "width":50,
                 "x":-50,
                 "y":100
                }, 
                {
                 "height":50,
                 "id":3624,
                 "name":"",
                 "rotation":0,
                 "type":"",
                 "visible":true,
                 "width":50,
                 "x":-100,
                 "y":100
                }, 
                {
                 "height":50,
                 "id":3625,
                 "name":"",
                 "rotation":0,
                 "type":"",
                 "visible":true,
                 "width":50,
                 "x":-100,
                 "y":150
                }, 
                {
                 "height":50,
                 "id":3626,
                 "name":"",
                 "rotation":0,
                 "type":"",
                 "visible":true,
                 "width":50,
                 "x":-50,
                 "y":150
                }, 
                {
                 "height":50,
                 "id":3627,
                 "name":"",
                 "rotation":0,
                 "type":"",
                 "visible":true,
                 "width":50,
                 "x":0,
                 "y":150
                }, 
                {
                 "height":50,
                 "id":3628,
                 "name":"",
                 "rotation":0,
                 "type":"",
                 "visible":true,
                 "width":50,
                 "x":-50,
                 "y":200
                }, 
                {
                 "height":50,
                 "id":3629,
                 "name":"",
                 "rotation":0,
                 "type":"",
                 "visible":true,
                 "width":50,
                 "x":0,
                 "y":200
                }, 
                {
                 "height":50,
                 "id":3630,
                 "name":"",
                 "rotation":0,
                 "type":"",
                 "visible":true,
                 "width":50,
                 "x":50,
                 "y":200
                }, 
                {
                 "height":50,
                 "id":3631,
                 "name":"",
                 "rotation":0,
                 "type":"",
                 "visible":true,
                 "width":50,
                 "x":50,
                 "y":250
                }, 
                {
                 "height":50,
                 "id":3632,
                 "name":"",
                 "rotation":0,
                 "type":"",
                 "visible":true,
                 "width":50,
                 "x":-50,
                 "y":250
                }, 
                {
                 "height":50,
                 "id":3633,
                 "name":"",
                 "rotation":0,
                 "type":"",
                 "visible":true,
                 "width":50,
                 "x":100,
                 "y":150
                }, 
                {
                 "height":50,
                 "id":3634,
                 "name":"",
                 "rotation":0,
                 "type":"",
                 "visible":true,
                 "width":50,
                 "x":100,
                 "y":200
                }, 
                {
                 "height":50,
                 "id":3635,
                 "name":"",
                 "rotation":0,
                 "type":"",
                 "visible":true,
                 "width":50,
                 "x":100,
                 "y":250
                }, 
                {
                 "height":50,
                 "id":3636,
                 "name":"",
                 "rotation":0,
                 "type":"",
                 "visible":true,
                 "width":50,
                 "x":150,
                 "y":200
                }, 
                {
                 "height":50,
                 "id":3637,
                 "name":"",
                 "rotation":0,
                 "type":"",
                 "visible":true,
                 "width":50,
                 "x":150,
                 "y":250
                }, 
                {
                 "height":50,
                 "id":3638,
                 "name":"",
                 "rotation":0,
                 "type":"",
                 "visible":true,
                 "width":50,
                 "x":200,
                 "y":200
                }, 
                {
                 "height":50,
                 "id":3639,
                 "name":"",
                 "rotation":0,
                 "type":"",
                 "visible":true,
                 "width":50,
                 "x":250,
                 "y":200
                }, 
                {
                 "height":50,
                 "id":3640,
                 "name":"",
                 "rotation":0,
                 "type":"",
                 "visible":true,
                 "width":50,
                 "x":250,
                 "y":150
                }, 
                {
                 "height":50,
                 "id":3641,
                 "name":"",
                 "rotation":0,
                 "type":"",
                 "visible":true,
                 "width":50,
                 "x":200,
                 "y":150
                }, 
                {
                 "height":50,
                 "id":3642,
                 "name":"",
                 "rotation":0,
                 "type":"",
                 "visible":true,
                 "width":50,
                 "x":300,
                 "y":200
                }, 
                {
                 "height":50,
                 "id":3643,
                 "name":"",
                 "rotation":0,
                 "type":"",
                 "visible":true,
                 "width":50,
                 "x":350,
                 "y":200
                }, 
                {
                 "height":50,
                 "id":3644,
                 "name":"",
                 "rotation":0,
                 "type":"",
                 "visible":true,
                 "width":50,
                 "x":350,
                 "y":250
                }, 
                {
                 "height":50,
                 "id":3645,
                 "name":"",
                 "rotation":0,
                 "type":"",
                 "visible":true,
                 "width":50,
                 "x":300,
                 "y":250
                }, 
                {
                 "height":50,
                 "id":3646,
                 "name":"",
                 "rotation":0,
                 "type":"",
                 "visible":true,
                 "width":50,
                 "x":350,
                 "y":150
                }, 
                {
                 "height":50,
                 "id":3647,
                 "name":"",
                 "rotation":0,
                 "type":"",
                 "visible":true,
                 "width":50,
                 "x":400,
                 "y":200
                }, 
                {
                 "height":50,
                 "id":3648,
                 "name":"",
                 "rotation":0,
                 "type":"",
                 "visible":true,
                 "width":50,
                 "x":450,
                 "y":200
                }, 
                {
                 "height":50,
                 "id":3649,
                 "name":"",
                 "rotation":0,
                 "type":"",
                 "visible":true,
                 "width":50,
                 "x":450,
                 "y":250
                }, 
                {
                 "height":50,
                 "id":3650,
                 "name":"",
                 "rotation":0,
                 "type":"",
                 "visible":true,
                 "width":50,
                 "x":400,
                 "y":250
                }, 
                {
                 "height":50,
                 "id":3651,
                 "name":"",
                 "rotation":0,
                 "type":"",
                 "visible":true,
                 "width":50,
                 "x":300,
                 "y":0
                }, 
                {
                 "height":50,
                 "id":3652,
                 "name":"",
                 "rotation":0,
                 "type":"",
                 "visible":true,
                 "width":50,
                 "x":300,
                 "y":50
                }, 
                {
                 "height":50,
                 "id":3653,
                 "name":"",
                 "rotation":0,
                 "type":"",
                 "visible":true,
                 "width":50,
                 "x":250,
                 "y":50
                }, 
                {
                 "height":50,
                 "id":3654,
                 "name":"",
                 "rotation":0,
                 "type":"",
                 "visible":true,
                 "width":50,
                 "x":250,
                 "y":0
                }, 
                {
                 "height":50,
                 "id":3655,
                 "name":"",
                 "rotation":0,
                 "type":"",
                 "visible":true,
                 "width":50,
                 "x":250,
                 "y":-50
                }, 
                {
                 "height":50,
                 "id":3674,
                 "name":"",
                 "rotation":0,
                 "type":"",
                 "visible":true,
                 "width":50,
                 "x":350,
                 "y":-200
                }, 
                {
                 "height":50,
                 "id":3675,
                 "name":"",
                 "rotation":0,
                 "type":"",
                 "visible":true,
                 "width":50,
                 "x":300,
                 "y":-200
                }],
         "opacity":1,
         "type":"objectgroup",
         "visible":true,
         "x":0,
         "y":0
        }, 
        {
         "color":"#ffff00",
         "draworder":"topdown",
         "id":10,
         "name":"splitter",
         "objects":[],
         "opacity":1,
         "type":"objectgroup",
         "visible":true,
         "x":0,
         "y":0
        }],
 "nextlayerid":11,
 "nextobjectid":3789,
 "orientation":"orthogonal",
 "renderorder":"right-down",
 "tiledversion":"1.4.3",
 "tileheight":50,
 "tilesets":[],
 "tilewidth":50,
 "type":"map",
 "version":1.1,
 "width":16
}